Workbook

Sheet Cover
B7: Client: | D7: Tim Hortons / RBI
B8: Date of Valuation | D8: 45261
B9: Owner | D9: Restaurant Brands International Inc. .
B11: Market entry and GTM
B14: INDEX
B15: 1 | C15: Assumptions
B16: =B15+1 -> 2 | C16: Market Sizing
B17: =B16+1 -> 3 | C17: Competitive Landscape
B18: =B17+1 -> 4 | C18: Product Profitability
B19: =B18+1 -> 5 | C19: GTM & City Prioritisation
B20: =B19+1 -> 6 | C20: Unit Economics

Sheet Assumptions
B2: ASSUMPTIONS
B3: Tim Hortons India Market Entry
A5: (Unless Otherwise specified, all financials are in ₹) | D5: Units | E5: Value | G5: Source & Rationale
A7: 1 | B7: India Café Market
B9: India F&B market size (2023) | D9: ₹ Cr | E9: 90000 | G9: NRAI India Food Services Report 2023; total organised+unorganised F&B
B10: Café segment share of F&B | D10: % | E10: 0.05 | G10: Euromonitor / Technavio: café & bar segment 5% of total F&B spend
B11: India café market size (2023) | D11: ₹ Cr | E11: =E10*E9 -> 4500
B12: India café market CAGR (2023-28) | D12: % | E12: 0.12 | G12: Redseer Strategy Consultants
B13: Urban café penetration (% urban pop) | D13: % | E13: 0.08 | G13: BCG India Consumer Sentiment 2023; almost 8% urban adults visit café monthly
A16: 2 | B16: Consumer Behaviour
B18: Avg ticket size (premium café) | D18: ₹ | E18: 450
B19: Avg ticket size (mid-market café) | D19: ₹ | E19: 220
B20: Tim Hortons target ticket size | D20: ₹ | E20: 280
B21: Coffee drinker share – urban India | D21: % | E21: 0.32
B22: Morning visit share (breakfast daypart) | D22: % | E22: 0.38
A25: 3 | B25: Store Economics
B27: Setup cost per store – metro (₹ lakh) | D27: ₹ Lakh | E27: 150
B28: Franchise/royalty fee (% of revenue) | D28: % | E28: 0.06
B29: Lease cost – metro high street (₹/sqft/mo) | D29: ₹/sqft/mo | E29: 300
B30: Store size (sqft) | D30: sqft | E30: 1200
B31: Staff count per store | D31: FTEs | E31: 12
B32: Avg staff cost p.m. per FTE (₹) | D32: ₹/mo | E32: 22000 | G32: Teamlease F&B Salary Report 2023; café staff ₹18k-26k blended
B33: Daily footfall assumption – Year 1 | D33: Customers/day | E33: 220 | G33: New store ramp; comparable Starbucks India outlet launch data 200-250/day
B34: Footfall ramp – Year 2 growth | D34: % | E34: 0.2
B35: COGS as % of revenue | D35: % | E35: 0.3
B36: Operating days per year | D36: Days | E36: 350
A39: 4 | B39: Market Entry
B41: Phase 1 cities (Year 1) | E41: Delhi NCR, Mumbai
B42: Phase 1 target outlets (Year 1) | D42: # | E42: 8
B43: Phase 2 cities (Year 2) | E43: Bengaluru, Pune
B44: Phase 2 target outlets (Year 2) | D44: # | E44: 20
A47: 5 | B47: Competitive
B49: Starbucks India outlets (2023) | D49: Stores | E49: 390
B50: CCD outlets (2023) | D50: Stores | E50: 450
B51: Starbucks avg ticket India (₹) | D51: ₹ | E51: 450
A54: 6 | B54: Products
B56: Tim Hortons classic coffee COGS ratio | D56: % | E56: 0.27
B57: Timbits donut COGS ratio | D57: % | E57: 0.35
B58: Localisation cost premium - food items | D58: % | E58: 0.08
B59: Cold beverage margin premium | D59: % | E59: 0.05

Sheet Market Sizing
B2: INDIA CAFÉ MARKET SIZING
B3: TAM / SAM / SOM
E4: Base Year
A5: =Assumptions!A5 -> (Unless Otherwise specified, all financials are in ₹) | E5: =Cover!D8 -> 45261 | F5: =EOMONTH(E5,12) -> 45657 | G5: =EOMONTH(F5,12) -> 46022 | H5: =EOMONTH(G5,12) -> 46387 | I5: =EOMONTH(H5,12) -> 46752 | J5: =EOMONTH(I5,12) -> 47118
A7: A | B7: Top-down Market Sizing
B9: India F&B Market | D9: ₹ Cr | E9: =Assumptions!E9 -> 90000 | F9: =E9*(1+0.09) -> 98100 | G9: =F9*(1+0.09) -> 106929 | H9: =G9*(1+0.09) -> 116552.61 | I9: =H9*(1+0.09) -> 127042.34 | J9: =I9*(1+0.09) -> 138476.16
B10: Café Segment Share | D10: % | E10: =Assumptions!E10 -> 0.05
B11: India Café Market TAM | D11: ₹ Cr | E11: =$E$10*E9 -> 4500 | F11: =$E$10*F9 -> 4905 | G11: =$E$10*G9 -> 5346.45 | H11: =$E$10*H9 -> 5827.6305 | I11: =$E$10*I9 -> 6352.1172 | J11: =$E$10*J9 -> 6923.8078
B12: Organised Café Share | D12: % | E12: 0.35 | F12: 0.37 | G12: 0.39 | H12: 0.41 | I12: 0.43 | J12: 0.45
B13: Organised Café Market SAM | D13: ₹ Cr | E13: =E12*E11 -> 1575 | F13: =F12*F11 -> 1814.85 | G13: =G12*G11 -> 2085.1155 | H13: =H12*H11 -> 2389.3285 | I13: =I12*I11 -> 2731.4104 | J13: =J12*J11 -> 3115.7135
B14: Tim Hortons Achievable Share | D14: % | E14: 0.005 | F14: 0.01 | G14: 0.02 | H14: 0.035 | I14: 0.05 | J14: 0.07
B15: Tim Hortons SOM | D15: ₹ Cr | E15: =E14*E13 -> 7.875 | F15: =F14*F13 -> 18.1485 | G15: =G14*G13 -> 41.70231 | H15: =H14*H13 -> 83.626498 | I15: =I14*I13 -> 136.57052 | J15: =J14*J13 -> 218.09995
A18: B | B18: Bottom-up Market Sizing
B20: Number of Tim Hortons stores | F20: =Assumptions!E42 -> 8 | G20: 28 | H20: 55 | I20: 90 | J20: 140 | L20: Phase plan in GTM sheet
B21: Avg daily footfall / store | F21: =Assumptions!E19 -> 220 | G21: 264 | H21: 290 | I21: 310 | J21: 330
B22: Avg ticket size (₹) | F22: =Assumptions!E20 -> 280 | G22: 295 | H22: 310 | I22: 325 | J22: 340
B23: Operating days/year | F23: 350
B24: Revenue per store (₹ Cr) | D24: ₹ Cr | F24: =$F$23*F22*F21/10000000 -> 2.156 | G24: =$F$23*G22*G21/10000000 -> 2.7258 | H24: =$F$23*H22*H21/10000000 -> 3.1465 | I24: =$F$23*I22*I21/10000000 -> 3.52625 | J24: =$F$23*J22*J21/10000000 -> 3.927
B25: Total network revenue (₹ Cr) | D25: ₹ Cr | F25: =F24*F20 -> 17.248 | G25: =G24*G20 -> 76.3224 | H25: =H24*H20 -> 173.0575 | I25: =I24*I20 -> 317.3625 | J25: =J24*J20 -> 549.78

Sheet Competitive Landscape
N1: x
B2: COMPETITIVE LANDSCAPE | N2: x
B3: India Café Market vs. Tim Hortons | N3: x
A5: =Assumptions!A5 -> (Unless Otherwise specified, all financials are in ₹) | E5: Outlets (India) | F5: Avg Ticket (₹) | G5: Positioning | H5: Core Strength | I5: Core Weakness | J5: Tim Hortons Overlap | K5: Threat to TH | L5: Opportunity Gap | N5: x
N6: x
A7: Competitor | N7: x
N8: x
B9: Starbucks India | E9: =Assumptions!E49 -> 390 | F9: =Assumptions!E51 -> 450 | G9: Premium / aspirational | H9: Global brand; loyalty ecosystem; Tata partnership depth | I9: High price point limits mass appeal; limited menu localisation | J9: Premium beverages; urban affluent | K9: HIGH | L9: Affordable everyday positioning; Tier 2 expansion; breakfast | N9: x
B10: Café Coffee Day | E10: =Assumptions!E50 -> 450 | F10: 220 | G10: Value / everyday | H10: Largest network; local brand trust; affordable | I10: Financial stress; dated store experience; weak marketing | J10: Affordable positioning; daily coffee | K10: MED | L10: Superior product quality; global brand credibility; digital | N10: x
B11: Blue Tokai | E11: 80 | F11: 380 | G11: Specialty / artisanal | H11: High quality; roastery story; urban cult following | I11: Small scale; niche appeal; no mass-market pricing | J11: Specialty coffee drinkers | K11: LOW | L11: Scale; accessibility; non-coffee items (Timbits/food) | N11: x
B12: Third Wave Coffee | E12: 120 | F12: 350 | G12: Neo-premium / experience | H12: Young brand; strong D2C; influencer-driven growth | I12: Limited geography; premium pricing in non-metro pushback | J12: Coffee connoisseurs; youth | K12: LOW-MED | L12: Tier 1 expansion; food + coffee bundling at accessible price | N12: x
B13: McDonald's McCafé | E13: 350 | F13: 150 | G13: Convenience / value | H13: Massive footfall via McDonald's; low price | I13: Perceived as fast-food add-on; no café ambiance | J13: Quick grab-and-go; value seekers | K13: MED-HIGH | L13: Café experience + quality coffee; Timbits complement baked | N13: x
B14: Barista | E14: 200 | F14: 260 | G14: Mid-premium / familiar | H14: Legacy brand; mall presence | I14: Weak brand investment; menu stale; no innovation | J14: Mid-market; mall consumers | K14: LOW | L14: Innovation; Tim Hortons brand freshness; breakfast range | N14: x
B15: Dunkin' India | E15: 30 | F15: 250 | G15: Value-premium / American | H15: Parent brand recognition; donuts | I15: Very limited presence; supply chain issues in India | J15: Donuts + coffee combo | K15: LOW | L15: Direct overlap but TH far stronger globally; scale advantage | N15: x
N16: x
N17: x
N18: x
B19: Strength | E19: Why It Matters in India | N19: x
A21: - | B21: Affordable Premium Positioning | E21: ₹250-300 ticket hits the sweet spot below Starbucks and above CCD – India's fastest-growing consumer segment | N21: x
A22: - | B22: Breakfast + Coffee Bundle | E22: No incumbent owns the morning breakfast occasion at scale. Timbits + coffee as habitual daily combo is untapped | N22: x
A23: - | B23: RBI Parent Ecosystem | E23: Parent RBI owns Burger King India (300+ outlets) – potential cross-location synergies, shared real estate pipeline | N23: x
A24: - | B24: Menu Localisation Capability | E24: RBI's India F&B experience (BK India) accelerates FSSAI compliance, local sourcing, veg menu build | N24: x
A25: - | B25: Global Brand Recognition | E25: Among Indian outbound travellers & NRIs – Tim Hortons has high awareness. Strong brand pull for aspirational consumers | N25: x
A26: - | B26: Digital & Loyalty Infrastructure | E26: Tim Hortons app with gamified loyalty is replicable in India – key for Gen Z / Millennial retention | N26: x
N27: x
N28: x
N29: x

Sheet Product Profitability
B2: PRODUCT PROFITABILITY MATRIX
B3: Tim Hortons India
A4: =Assumptions!A5 -> (Unless Otherwise specified, all financials are in ₹) | E4: India Sell Price (₹) | F4: Estimated COGS (₹) | G4: Gross Margin (%) | H4: Consumer Demand Fit (1-5) | I4: Localisation Ease (1-5) | J4: Competitive Intensity (1-5, 5=low) | K4: Expected Volume (1-5) | L4: Brand Identity Fit (1-5) | M4: Weighted Opp Score | N4: Recommendation
B6: Weightage | G6: 0.2 | H6: 0.2 | I6: 0.15 | J6: 0.2 | K6: 0.15 | L6: 0.1
A8: Product Category
B10: Classic Drip Coffee (Hot) | E10: 120 | F10: =E10*Assumptions!E56 -> 32.4 | G10: =(E10-F10)/E10 -> 0.73 | H10: 5 | I10: 4 | J10: 4 | K10: 5 | L10: 5 | M10: =(G10/5)*$G$6+(H10/5)*$H$6+(I10/5)*$I$6+(J10/5)*$J$6+(K10/5)*$K$6+(L10/5)*$L$6 -> 0.7592 | N10: =IF(M10>=0.75,"🟢 PRIORITY LAUNCH",IF(M10>=0.6,"🟡 INCLUDE IN MENU","🔴 DEFER / TEST")) -> 🟢 PRIORITY LAUNCH
B11: Espresso-based Drinks (Latte/Cap) | E11: 180 | F11: =E11*0.3 -> 54 | G11: =(E11-F11)/E11 -> 0.7 | H11: 4 | I11: 4 | J11: 3 | K11: 4 | L11: 5 | M11: =(G11/5)*$G$6+(H11/5)*$H$6+(I11/5)*$I$6+(J11/5)*$J$6+(K11/5)*$K$6+(L11/5)*$L$6 -> 0.648 | N11: =IF(M11>=0.75,"🟢 PRIORITY LAUNCH",IF(M11>=0.6,"🟡 INCLUDE IN MENU","🔴 DEFER / TEST")) -> 🟡 INCLUDE IN MENU
B12: Cold Brew / Iced Coffee | E12: 200 | F12: =E12*0.27 -> 54 | G12: =(E12-F12)/E12 -> 0.73 | H12: 5 | I12: 4 | J12: 3 | K12: 4 | L12: 4 | M12: =(G12/5)*$G$6+(H12/5)*$H$6+(I12/5)*$I$6+(J12/5)*$J$6+(K12/5)*$K$6+(L12/5)*$L$6 -> 0.6692 | N12: =IF(M12>=0.75,"🟢 PRIORITY LAUNCH",IF(M12>=0.6,"🟡 INCLUDE IN MENU","🔴 DEFER / TEST")) -> 🟡 INCLUDE IN MENU
B13: Timbits (Mini Donuts) | E13: 80 | F13: =E13*0.35 -> 28 | G13: =(E13-F13)/E13 -> 0.65 | H13: 5 | I13: 3 | J13: 3 | K13: 5 | L13: 5 | M13: =(G13/5)*$G$6+(H13/5)*$H$6+(I13/5)*$I$6+(J13/5)*$J$6+(K13/5)*$K$6+(L13/5)*$L$6 -> 0.686 | N13: =IF(M13>=0.75,"🟢 PRIORITY LAUNCH",IF(M13>=0.6,"🟡 INCLUDE IN MENU","🔴 DEFER / TEST")) -> 🟡 INCLUDE IN MENU
B14: Timbits (Indian Flavour - Gulab/Mango) | E14: 90 | F14: =E14*(Assumptions!E57+Assumptions!E58) -> 38.7 | G14: =(E14-F14)/E14 -> 0.57 | H14: 4 | I14: 5 | J14: 3 | K14: 4 | L14: 5 | M14: =(G14/5)*$G$6+(H14/5)*$H$6+(I14/5)*$I$6+(J14/5)*$J$6+(K14/5)*$K$6+(L14/5)*$L$6 -> 0.6728 | N14: =IF(M14>=0.75,"🟢 PRIORITY LAUNCH",IF(M14>=0.6,"🟡 INCLUDE IN MENU","🔴 DEFER / TEST")) -> 🟡 INCLUDE IN MENU
B15: Classic Breakfast Sandwich | E15: 160 | F15: =E15*0.38 -> 60.8 | G15: =(E15-F15)/E15 -> 0.62 | H15: 3 | I15: 3 | J15: 3 | K15: 3 | L15: 3 | M15: =(G15/5)*$G$6+(H15/5)*$H$6+(I15/5)*$I$6+(J15/5)*$J$6+(K15/5)*$K$6+(L15/5)*$L$6 -> 0.5048 | N15: =IF(M15>=0.75,"🟢 PRIORITY LAUNCH",IF(M15>=0.6,"🟡 INCLUDE IN MENU","🔴 DEFER / TEST")) -> 🔴 DEFER / TEST
B16: Vegetarian Breakfast Wrap (India-specific) | E16: 150 | F16: =E16*0.4 -> 60 | G16: =(E16-F16)/E16 -> 0.6 | H16: 4 | I16: 4 | J16: 4 | K16: 4 | L16: 4 | M16: =(G16/5)*$G$6+(H16/5)*$H$6+(I16/5)*$I$6+(J16/5)*$J$6+(K16/5)*$K$6+(L16/5)*$L$6 -> 0.664 | N16: =IF(M16>=0.75,"🟢 PRIORITY LAUNCH",IF(M16>=0.6,"🟡 INCLUDE IN MENU","🔴 DEFER / TEST")) -> 🟡 INCLUDE IN MENU
B17: Baked Goods (Muffins / Croissants) | E17: 120 | F17: =E17*0.36 -> 43.2 | G17: =(E17-F17)/E17 -> 0.64 | H17: 3 | I17: 3 | J17: 3 | K17: 3 | L17: 2 | M17: =(G17/5)*$G$6+(H17/5)*$H$6+(I17/5)*$I$6+(J17/5)*$J$6+(K17/5)*$K$6+(L17/5)*$L$6 -> 0.4856 | N17: =IF(M17>=0.75,"🟢 PRIORITY LAUNCH",IF(M17>=0.6,"🟡 INCLUDE IN MENU","🔴 DEFER / TEST")) -> 🔴 DEFER / TEST
B18: Cold Beverages (Smoothies / Frappes) | E18: 220 | F18: =E18*(Assumptions!E56-Assumptions!E59) -> 48.4 | G18: =(E18-F18)/E18 -> 0.78 | H18: 4 | I18: 3 | J18: 3 | K18: 4 | L18: 3 | M18: =(G18/5)*$G$6+(H18/5)*$H$6+(I18/5)*$I$6+(J18/5)*$J$6+(K18/5)*$K$6+(L18/5)*$L$6 -> 0.5812 | N18: =IF(M18>=0.75,"🟢 PRIORITY LAUNCH",IF(M18>=0.6,"🟡 INCLUDE IN MENU","🔴 DEFER / TEST")) -> 🔴 DEFER / TEST
B19: Chai Latte (India-localised) | E19: 130 | F19: =E19*0.32 -> 41.6 | G19: =(E19-F19)/E19 -> 0.68 | H19: 5 | I19: 5 | J19: 2 | K19: 5 | L19: 3 | M19: =(G19/5)*$G$6+(H19/5)*$H$6+(I19/5)*$I$6+(J19/5)*$J$6+(K19/5)*$K$6+(L19/5)*$L$6 -> 0.6672 | N19: =IF(M19>=0.75,"🟢 PRIORITY LAUNCH",IF(M19>=0.6,"🟡 INCLUDE IN MENU","🔴 DEFER / TEST")) -> 🟡 INCLUDE IN MENU
B20: Combo Meal (Coffee + Timbits) | E20: 190 | F20: =E20*0.31 -> 58.9 | G20: =(E20-F20)/E20 -> 0.69 | H20: 5 | I20: 4 | J20: 4 | K20: 5 | L20: 5 | M20: =(G20/5)*$G$6+(H20/5)*$H$6+(I20/5)*$I$6+(J20/5)*$J$6+(K20/5)*$K$6+(L20/5)*$L$6 -> 0.7576 | N20: =IF(M20>=0.75,"🟢 PRIORITY LAUNCH",IF(M20>=0.6,"🟡 INCLUDE IN MENU","🔴 DEFER / TEST")) -> 🟢 PRIORITY LAUNCH

Sheet GTM & City Prioritisation
B2: GTM STRATEGY & CITY PRIORITISATION
B3: Tim Hortons India
A5: =Assumptions!A5 -> (Unless Otherwise specified, all financials are in ₹) | E5: Café Culture Maturity (1-5) | F5: Disposable Income (1-5) | G5: TH Brand Awareness (1-5) | H5: RE Cost Feasibility (1-5) | I5: Competition Intensity (1-5) | J5: Weighted Priority Score | K5: Phase Recommendation
A7: City Prioritisation Matrix
B9: City
B10: Mumbai | E10: 5 | F10: 5 | G10: 4 | H10: 2 | I10: 5 | J10: =(E10*0.25+F10*0.25+G10*0.2+H10*0.15+I10*0.15)/5 -> 0.87 | K10: Phase 1 – Year 1
B11: Delhi / NCR | E11: 5 | F11: 5 | G11: 5 | H11: 3 | I11: 4 | J11: =(E11*0.25+F11*0.25+G11*0.2+H11*0.15+I11*0.15)/5 -> 0.91 | K11: Phase 1 – Year 1
B12: Bengaluru | E12: 5 | F12: 5 | G12: 4 | H12: 3 | I12: 4 | J12: =(E12*0.25+F12*0.25+G12*0.2+H12*0.15+I12*0.15)/5 -> 0.87 | K12: Phase 1 – Year 1
B13: Hyderabad | E13: 4 | F13: 4 | G13: 3 | H13: 4 | I13: 3 | J13: =(E13*0.25+F13*0.25+G13*0.2+H13*0.15+I13*0.15)/5 -> 0.73 | K13: Phase 2 – Year 2
B14: Pune | E14: 4 | F14: 4 | G14: 3 | H14: 4 | I14: 3 | J14: =(E14*0.25+F14*0.25+G14*0.2+H14*0.15+I14*0.15)/5 -> 0.73 | K14: Phase 2 – Year 2
B15: Chennai | E15: 3 | F15: 4 | G15: 3 | H15: 4 | I15: 3 | J15: =(E15*0.25+F15*0.25+G15*0.2+H15*0.15+I15*0.15)/5 -> 0.68 | K15: Phase 3 – Year 3+
B16: Kolkata | E16: 3 | F16: 3 | G16: 3 | H16: 4 | I16: 3 | J16: =(E16*0.25+F16*0.25+G16*0.2+H16*0.15+I16*0.15)/5 -> 0.63 | K16: Phase 3 – Year 3+
B17: Chandigarh | E17: 4 | F17: 4 | G17: 4 | H17: 5 | I17: 2 | J17: =(E17*0.25+F17*0.25+G17*0.2+H17*0.15+I17*0.15)/5 -> 0.77 | K17: Phase 2 – Year 2
B18: Ahmedabad | E18: 3 | F18: 4 | G18: 3 | H18: 4 | I18: 2 | J18: =(E18*0.25+F18*0.25+G18*0.2+H18*0.15+I18*0.15)/5 -> 0.65 | K18: Phase 3 – Year 3+
B19: Jaipur | E19: 3 | F19: 3 | G19: 3 | H19: 5 | I19: 2 | J19: =(E19*0.25+F19*0.25+G19*0.2+H19*0.15+I19*0.15)/5 -> 0.63 | K19: Phase 3 – Year 3+
A22: GTM Phasing Plan
B24: Phases | E24: Timeline | F24: Cities | G24: No. of Stores | H24: Entry Mode | I24: Investment Focus | J24: Risk Flags | K24: Key Milestones
B25: Phase 1 – Pilot | E25: Q1 2024 – Q4 2024 | F25: Delhi NCR + Mumbai | G25: =Assumptions!E42 -> 8 | H25: Master Franchise / JV with Devyani/Jubilant | I25: Brand building; store ops; supply chain setup | J25: Franchisee quality; FSSAI approvals; supply chain gaps | K25: 8 stores live; Unit economics validated; App launched in India; Local menu (Chai Latte, Veg wrap) tested
B26: Phase 2 – Scale | E26: Q1 2025 – Q4 2025 | F26: + Bengaluru + Pune | G26: =Assumptions!E44 -> 20 | H26: Franchise expansion; airport & mall prioritisation | I26: Marketing spend; menu localisation; supply scale | J26: Competition response from Starbucks/McCafé; real estate costs | K26: 28 total stores; Breakfast daypart >35% mix; Timbits becoming signature product; Loyalty app MAU >50k
B27: Phase 3 – Accelerate | E27: 2026–2028 | F27: + Hyderabad, Chennai, Tier 2 | G27: 90-140 stores (see Market Sizing sheet) | H27: Mix of franchise + company-owned flagships | I27: Digital ordering; delivery tie-up (Swiggy/Zomato); loyalty monetisation | J27: Franchisor quality control at scale; margin pressure | K27: National brand; 5%+ organised market share; Drive-thru pilots in suburban markets

Sheet Unit Economics
B2: UNIT ECONOMICS
B3: Single Store P&L Model (Tim Hortons India)
A5: (Unless Otherwise specified, all financials are in ₹) | E5: Monthly (₹) | F5: Annual (₹) | G5: % of Revenue
F6: 12
A7: Revenue
B9: Daily Footfall (customers) | C9: # | E9: =Assumptions!E33 -> 220
B10: Avg Ticket Size (₹) | C10: ₹ | E10: =Assumptions!E20 -> 280
B11: Operating Days / Month | C11: # | E11: 29
B12: Gross Revenue / Month (₹) | C12: ₹ | E12: =E11*E10*E9 -> 1786400 | F12: =E12*$F$6 -> 21436800
A14: Cost of Goods
B16: COGS % of Revenue | C16: % | E16: =Assumptions!E35 -> 0.3
B17: COGS Amount | C17: ₹ | E17: =E12*E16 -> 535920 | F17: =E17*$F$6 -> 6431040
B18: Gross Profit | C18: ₹ | E18: =E12-E17 -> 1250480 | F18: =E18*$F$6 -> 15005760
B19: Gross Margin % | C19: % | E19: =E18/E12 -> 0.7
A21: Operating Expenses
B23: Rent | E23: =Assumptions!E29*Assumptions!E30 -> 360000 | F23: =E23*$F$6 -> 4320000 | G23: =F23/$F$12 -> 0.20152262
B24: Staff Cost | E24: =Assumptions!E31*Assumptions!E32 -> 264000 | F24: =E24*$F$6 -> 3168000 | G24: =F24/$F$12 -> 0.14778325
B25: Franchise / Royalty Fee | E25: =E12*Assumptions!E28 -> 107184 | F25: =E25*$F$6 -> 1286208 | G25: =F25/$F$12 -> 0.06
B26: Marketing & Promotions | E26: =E12*0.05 -> 89320 | F26: =E26*$F$6 -> 1071840 | G26: =F26/$F$12 -> 0.05
B27: Utilities & Maintenance | E27: 35000 | F27: =E27*$F$6 -> 420000 | G27: =F27/$F$12 -> 0.019592476
B28: Other Opex | E28: =E12*0.03 -> 53592 | F28: =E28*$F$6 -> 643104 | G28: =F28/$F$12 -> 0.03
B29: Total Opex | E29: =SUM(E23:E28) -> 909096 | F29: =SUM(F23:F28) -> 10909152 | G29: =F29/$F$12 -> 0.50889834
A31: Profitability
B33: EBITDA (₹) | C33: ₹ | E33: =E18-E29 -> 341384 | F33: =F18-F29 -> 4096608
B34: EBITDA Margin % | C34: % | E34: =E33/E12 -> 0.19110166 | F34: =F33/F12 -> 0.19110166
A36: Setup & Payback
B38: Store Setup Cost | C38: ₹ | E38: =Assumptions!E27*100000 -> 15000000 | F38: =E38*$F$6 -> 180000000
B39: Monthly EBITDA (₹) | C39: ₹ | E39: =E33 -> 341384 | F39: =F33 -> 4096608
B40: Payback Period (months) | C40: Months | E40: =IF(E39>0,E38/E39,"Negative EBITDA") -> 43.93879
B41: Payback Period (years) | C41: Years | E41: =IF(ISNUMBER(E40),E40/12,"N/A") -> 3.6615659
